{
  "id": "homebase",
  "realm": "homebase",
  "enabled": true,
  "displayName": "HomeBase",
  "displayNameHtml": "<h1>HomeBase</h1>",
  "registrationAllowed": true,
  "registrationEmailAsUsername": true,
  "loginWithEmailAllowed": true,
  "duplicateEmailsAllowed": false,
  "resetPasswordAllowed": true,
  "editUsernameAllowed": false,
  "verifyEmail": true,
  "sslRequired": "none",
  "loginTheme": "homebase",
  "accountTheme": "homebase",
  "emailTheme": "homebase",
  "bruteForceProtected": true,
  "permanentLockout": false,
  "maxFailureWaitSeconds": 900,
  "failureFactor": 5,
  "waitIncrementSeconds": 60,
  "minimumQuickLoginWaitSeconds": 60,
  "maxDeltaTimeSeconds": 43200,
  "quickLoginCheckMilliSeconds": 1000,
  "accessTokenLifespan": 300,
  "accessTokenLifespanForImplicitFlow": 900,
  "ssoSessionIdleTimeout": 1800,
  "ssoSessionMaxLifespan": 36000,
  "offlineSessionIdleTimeout": 2592000,
  "offlineSessionMaxLifespan": 5184000,
  "accessCodeLifespan": 60,
  "accessCodeLifespanLogin": 1800,
  "accessCodeLifespanUserAction": 300,
  "actionTokenGeneratedByAdminLifespan": 43200,
  "actionTokenGeneratedByUserLifespan": 300,
  "revokeRefreshToken": true,
  "refreshTokenMaxReuse": 0,
  "internationalizationEnabled": true,
  "supportedLocales": ["en"],
  "defaultLocale": "en",
  "passwordPolicy": "length(8) and upperCase(1) and lowerCase(1) and digits(1) and specialChars(1)",
  "smtpServer": {},
  "eventsEnabled": true,
  "eventsExpiration": 604800,
  "enabledEventTypes": [
    "LOGIN",
    "LOGIN_ERROR",
    "REGISTER",
    "REGISTER_ERROR",
    "LOGOUT",
    "UPDATE_PASSWORD",
    "SEND_RESET_PASSWORD",
    "RESET_PASSWORD",
    "SEND_VERIFY_EMAIL",
    "VERIFY_EMAIL"
  ],
  "adminEventsEnabled": true,
  "adminEventsDetailsEnabled": true,
  "roles": {
    "realm": [
      {
        "name": "CUSTOMER",
        "description": "End customer / buyer",
        "composite": false,
        "clientRole": false
      },
      {
        "name": "SELLER",
        "description": "Supplier / seller on marketplace",
        "composite": false,
        "clientRole": false
      },
      {
        "name": "WAREHOUSE_STAFF",
        "description": "Warehouse floor worker",
        "composite": false,
        "clientRole": false
      },
      {
        "name": "WAREHOUSE_MANAGER",
        "description": "Warehouse supervisor",
        "composite": false,
        "clientRole": false
      },
      {
        "name": "OPS_AGENT",
        "description": "Operations support agent",
        "composite": false,
        "clientRole": false
      },
      {
        "name": "OPS_MANAGER",
        "description": "Operations manager",
        "composite": false,
        "clientRole": false
      },
      {
        "name": "FINANCE_ANALYST",
        "description": "Finance team member",
        "composite": false,
        "clientRole": false
      },
      {
        "name": "FINANCE_MANAGER",
        "description": "Finance team lead",
        "composite": false,
        "clientRole": false
      },
      {
        "name": "PLATFORM_ADMIN",
        "description": "Platform administrator",
        "composite": false,
        "clientRole": false
      },
      {
        "name": "SUPER_ADMIN",
        "description": "Full system access",
        "composite": false,
        "clientRole": false
      },
      {
        "name": "default-roles-homebase",
        "description": "${role_default-roles}",
        "composite": true,
        "composites": {
          "realm": ["CUSTOMER"]
        },
        "clientRole": false
      }
    ]
  },
  "defaultRole": {
    "name": "default-roles-homebase",
    "description": "${role_default-roles}",
    "composite": true,
    "composites": {
      "realm": ["CUSTOMER"]
    }
  },
  "groups": [
    {
      "name": "customers",
      "realmRoles": ["CUSTOMER"]
    },
    {
      "name": "sellers",
      "realmRoles": ["SELLER"]
    },
    {
      "name": "warehouse-team",
      "realmRoles": ["WAREHOUSE_STAFF"]
    },
    {
      "name": "ops-team",
      "realmRoles": ["OPS_AGENT"]
    },
    {
      "name": "finance-team",
      "realmRoles": ["FINANCE_ANALYST"]
    },
    {
      "name": "platform-admins",
      "realmRoles": ["PLATFORM_ADMIN", "SUPER_ADMIN"]
    }
  ],
  "users": [
    {
      "username": "customer@test.com",
      "email": "customer@test.com",
      "firstName": "Test",
      "lastName": "Customer",
      "enabled": true,
      "emailVerified": true,
      "credentials": [
        {
          "type": "password",
          "value": "Test@1234",
          "temporary": false
        }
      ],
      "realmRoles": ["CUSTOMER", "default-roles-homebase"],
      "groups": ["customers"]
    },
    {
      "username": "seller@test.com",
      "email": "seller@test.com",
      "firstName": "Test",
      "lastName": "Seller",
      "enabled": true,
      "emailVerified": true,
      "credentials": [
        {
          "type": "password",
          "value": "Test@1234",
          "temporary": false
        }
      ],
      "realmRoles": ["SELLER", "default-roles-homebase"],
      "groups": ["sellers"]
    },
    {
      "username": "warehouse@test.com",
      "email": "warehouse@test.com",
      "firstName": "Test",
      "lastName": "Warehouse",
      "enabled": true,
      "emailVerified": true,
      "credentials": [
        {
          "type": "password",
          "value": "Test@1234",
          "temporary": false
        }
      ],
      "realmRoles": ["WAREHOUSE_STAFF", "default-roles-homebase"],
      "groups": ["warehouse-team"]
    },
    {
      "username": "ops@test.com",
      "email": "ops@test.com",
      "firstName": "Test",
      "lastName": "Operations",
      "enabled": true,
      "emailVerified": true,
      "credentials": [
        {
          "type": "password",
          "value": "Test@1234",
          "temporary": false
        }
      ],
      "realmRoles": ["OPS_AGENT", "OPS_MANAGER", "default-roles-homebase"],
      "groups": ["ops-team"]
    },
    {
      "username": "finance@test.com",
      "email": "finance@test.com",
      "firstName": "Test",
      "lastName": "Finance",
      "enabled": true,
      "emailVerified": true,
      "credentials": [
        {
          "type": "password",
          "value": "Test@1234",
          "temporary": false
        }
      ],
      "realmRoles": ["FINANCE_ANALYST", "FINANCE_MANAGER", "default-roles-homebase"],
      "groups": ["finance-team"]
    },
    {
      "username": "admin@test.com",
      "email": "admin@test.com",
      "firstName": "Test",
      "lastName": "Admin",
      "enabled": true,
      "emailVerified": true,
      "credentials": [
        {
          "type": "password",
          "value": "Test@1234",
          "temporary": false
        }
      ],
      "realmRoles": ["PLATFORM_ADMIN", "SUPER_ADMIN", "default-roles-homebase"],
      "groups": ["platform-admins"]
    }
  ],
  "clients": [
    {
      "clientId": "storefront-web",
      "name": "Storefront Web",
      "description": "Customer-facing storefront application",
      "enabled": true,
      "publicClient": true,
      "clientAuthenticatorType": "client-secret",
      "standardFlowEnabled": true,
      "implicitFlowEnabled": false,
      "directAccessGrantsEnabled": false,
      "serviceAccountsEnabled": false,
      "protocol": "openid-connect",
      "rootUrl": "http://localhost:3000",
      "baseUrl": "http://localhost:3000",
      "redirectUris": ["http://localhost:3000/*"],
      "webOrigins": ["http://localhost:3000"],
      "attributes": {
        "pkce.code.challenge.method": "S256",
        "post.logout.redirect.uris": "http://localhost:3000/*"
      },
      "fullScopeAllowed": true,
      "defaultClientScopes": [
        "web-origins",
        "acr",
        "roles",
        "profile",
        "email"
      ],
      "optionalClientScopes": [
        "address",
        "phone",
        "offline_access",
        "microprofile-jwt"
      ]
    },
    {
      "clientId": "seller-web",
      "name": "Seller Central",
      "description": "Seller/supplier management application",
      "enabled": true,
      "publicClient": true,
      "clientAuthenticatorType": "client-secret",
      "standardFlowEnabled": true,
      "implicitFlowEnabled": false,
      "directAccessGrantsEnabled": false,
      "serviceAccountsEnabled": false,
      "protocol": "openid-connect",
      "rootUrl": "http://localhost:3002",
      "baseUrl": "http://localhost:3002",
      "redirectUris": ["http://localhost:3002/*"],
      "webOrigins": ["http://localhost:3002"],
      "attributes": {
        "pkce.code.challenge.method": "S256",
        "post.logout.redirect.uris": "http://localhost:3002/*"
      },
      "fullScopeAllowed": true,
      "defaultClientScopes": [
        "web-origins",
        "acr",
        "roles",
        "profile",
        "email"
      ],
      "optionalClientScopes": [
        "address",
        "phone",
        "offline_access",
        "microprofile-jwt"
      ]
    },
    {
      "clientId": "warehouse-web",
      "name": "Warehouse Management",
      "description": "Warehouse management system",
      "enabled": true,
      "publicClient": true,
      "clientAuthenticatorType": "client-secret",
      "standardFlowEnabled": true,
      "implicitFlowEnabled": false,
      "directAccessGrantsEnabled": false,
      "serviceAccountsEnabled": false,
      "protocol": "openid-connect",
      "rootUrl": "http://localhost:3003",
      "baseUrl": "http://localhost:3003",
      "redirectUris": ["http://localhost:3003/*"],
      "webOrigins": ["http://localhost:3003"],
      "attributes": {
        "pkce.code.challenge.method": "S256",
        "post.logout.redirect.uris": "http://localhost:3003/*"
      },
      "fullScopeAllowed": true,
      "defaultClientScopes": [
        "web-origins",
        "acr",
        "roles",
        "profile",
        "email"
      ],
      "optionalClientScopes": [
        "address",
        "phone",
        "offline_access",
        "microprofile-jwt"
      ]
    },
    {
      "clientId": "oms-web",
      "name": "Order Management",
      "description": "Operations management system",
      "enabled": true,
      "publicClient": true,
      "clientAuthenticatorType": "client-secret",
      "standardFlowEnabled": true,
      "implicitFlowEnabled": false,
      "directAccessGrantsEnabled": false,
      "serviceAccountsEnabled": false,
      "protocol": "openid-connect",
      "rootUrl": "http://localhost:3004",
      "baseUrl": "http://localhost:3004",
      "redirectUris": ["http://localhost:3004/*"],
      "webOrigins": ["http://localhost:3004"],
      "attributes": {
        "pkce.code.challenge.method": "S256",
        "post.logout.redirect.uris": "http://localhost:3004/*"
      },
      "fullScopeAllowed": true,
      "defaultClientScopes": [
        "web-origins",
        "acr",
        "roles",
        "profile",
        "email"
      ],
      "optionalClientScopes": [
        "address",
        "phone",
        "offline_access",
        "microprofile-jwt"
      ]
    },
    {
      "clientId": "finance-web",
      "name": "Finance Dashboard",
      "description": "Finance and settlement management",
      "enabled": true,
      "publicClient": true,
      "clientAuthenticatorType": "client-secret",
      "standardFlowEnabled": true,
      "implicitFlowEnabled": false,
      "directAccessGrantsEnabled": false,
      "serviceAccountsEnabled": false,
      "protocol": "openid-connect",
      "rootUrl": "http://localhost:3005",
      "baseUrl": "http://localhost:3005",
      "redirectUris": ["http://localhost:3005/*"],
      "webOrigins": ["http://localhost:3005"],
      "attributes": {
        "pkce.code.challenge.method": "S256",
        "post.logout.redirect.uris": "http://localhost:3005/*"
      },
      "fullScopeAllowed": true,
      "defaultClientScopes": [
        "web-origins",
        "acr",
        "roles",
        "profile",
        "email"
      ],
      "optionalClientScopes": [
        "address",
        "phone",
        "offline_access",
        "microprofile-jwt"
      ]
    },
    {
      "clientId": "platform-web",
      "name": "Platform Admin",
      "description": "Platform administration console",
      "enabled": true,
      "publicClient": true,
      "clientAuthenticatorType": "client-secret",
      "standardFlowEnabled": true,
      "implicitFlowEnabled": false,
      "directAccessGrantsEnabled": false,
      "serviceAccountsEnabled": false,
      "protocol": "openid-connect",
      "rootUrl": "http://localhost:3006",
      "baseUrl": "http://localhost:3006",
      "redirectUris": ["http://localhost:3006/*"],
      "webOrigins": ["http://localhost:3006"],
      "attributes": {
        "pkce.code.challenge.method": "S256",
        "post.logout.redirect.uris": "http://localhost:3006/*"
      },
      "fullScopeAllowed": true,
      "defaultClientScopes": [
        "web-origins",
        "acr",
        "roles",
        "profile",
        "email"
      ],
      "optionalClientScopes": [
        "address",
        "phone",
        "offline_access",
        "microprofile-jwt"
      ]
    },
    {
      "clientId": "homebase-backend",
      "name": "HomeBase Backend",
      "description": "Backend service account for server-to-server communication",
      "enabled": true,
      "publicClient": false,
      "clientAuthenticatorType": "client-secret",
      "secret": "homebase-backend-secret",
      "standardFlowEnabled": false,
      "implicitFlowEnabled": false,
      "directAccessGrantsEnabled": true,
      "serviceAccountsEnabled": true,
      "protocol": "openid-connect",
      "redirectUris": [],
      "webOrigins": [],
      "fullScopeAllowed": true,
      "defaultClientScopes": [
        "web-origins",
        "acr",
        "roles",
        "profile",
        "email"
      ],
      "optionalClientScopes": [
        "address",
        "phone",
        "offline_access",
        "microprofile-jwt"
      ]
    }
  ],
  "clientScopes": [
    {
      "name": "roles",
      "description": "OpenID Connect scope for add user roles to the access token",
      "protocol": "openid-connect",
      "attributes": {
        "include.in.token.scope": "false",
        "display.on.consent.screen": "true",
        "consent.screen.text": "${rolesScopeConsentText}"
      },
      "protocolMappers": [
        {
          "name": "realm roles",
          "protocol": "openid-connect",
          "protocolMapper": "oidc-usermodel-realm-role-mapper",
          "consentRequired": false,
          "config": {
            "multivalued": "true",
            "userinfo.token.claim": "true",
            "id.token.claim": "true",
            "access.token.claim": "true",
            "claim.name": "realm_access.roles",
            "jsonType.label": "String"
          }
        },
        {
          "name": "client roles",
          "protocol": "openid-connect",
          "protocolMapper": "oidc-usermodel-client-role-mapper",
          "consentRequired": false,
          "config": {
            "multivalued": "true",
            "userinfo.token.claim": "true",
            "id.token.claim": "true",
            "access.token.claim": "true",
            "claim.name": "resource_access.${client_id}.roles",
            "jsonType.label": "String"
          }
        },
        {
          "name": "audience resolve",
          "protocol": "openid-connect",
          "protocolMapper": "oidc-audience-resolve-mapper",
          "consentRequired": false,
          "config": {}
        }
      ]
    },
    {
      "name": "web-origins",
      "description": "OpenID Connect scope for add allowed web origins to the access token",
      "protocol": "openid-connect",
      "attributes": {
        "include.in.token.scope": "false",
        "display.on.consent.screen": "false"
      },
      "protocolMappers": [
        {
          "name": "allowed web origins",
          "protocol": "openid-connect",
          "protocolMapper": "oidc-allowed-origins-mapper",
          "consentRequired": false,
          "config": {}
        }
      ]
    },
    {
      "name": "profile",
      "description": "OpenID Connect built-in scope: profile",
      "protocol": "openid-connect",
      "attributes": {
        "include.in.token.scope": "true",
        "display.on.consent.screen": "true",
        "consent.screen.text": "${profileScopeConsentText}"
      },
      "protocolMappers": [
        {
          "name": "full name",
          "protocol": "openid-connect",
          "protocolMapper": "oidc-full-name-mapper",
          "consentRequired": false,
          "config": {
            "id.token.claim": "true",
            "access.token.claim": "true",
            "userinfo.token.claim": "true"
          }
        },
        {
          "name": "given name",
          "protocol": "openid-connect",
          "protocolMapper": "oidc-usermodel-attribute-mapper",
          "consentRequired": false,
          "config": {
            "userinfo.token.claim": "true",
            "user.attribute": "firstName",
            "id.token.claim": "true",
            "access.token.claim": "true",
            "claim.name": "given_name",
            "jsonType.label": "String"
          }
        },
        {
          "name": "family name",
          "protocol": "openid-connect",
          "protocolMapper": "oidc-usermodel-attribute-mapper",
          "consentRequired": false,
          "config": {
            "userinfo.token.claim": "true",
            "user.attribute": "lastName",
            "id.token.claim": "true",
            "access.token.claim": "true",
            "claim.name": "family_name",
            "jsonType.label": "String"
          }
        },
        {
          "name": "username",
          "protocol": "openid-connect",
          "protocolMapper": "oidc-usermodel-attribute-mapper",
          "consentRequired": false,
          "config": {
            "userinfo.token.claim": "true",
            "user.attribute": "username",
            "id.token.claim": "true",
            "access.token.claim": "true",
            "claim.name": "preferred_username",
            "jsonType.label": "String"
          }
        }
      ]
    },
    {
      "name": "email",
      "description": "OpenID Connect built-in scope: email",
      "protocol": "openid-connect",
      "attributes": {
        "include.in.token.scope": "true",
        "display.on.consent.screen": "true",
        "consent.screen.text": "${emailScopeConsentText}"
      },
      "protocolMappers": [
        {
          "name": "email",
          "protocol": "openid-connect",
          "protocolMapper": "oidc-usermodel-attribute-mapper",
          "consentRequired": false,
          "config": {
            "userinfo.token.claim": "true",
            "user.attribute": "email",
            "id.token.claim": "true",
            "access.token.claim": "true",
            "claim.name": "email",
            "jsonType.label": "String"
          }
        },
        {
          "name": "email verified",
          "protocol": "openid-connect",
          "protocolMapper": "oidc-usermodel-attribute-mapper",
          "consentRequired": false,
          "config": {
            "userinfo.token.claim": "true",
            "user.attribute": "emailVerified",
            "id.token.claim": "true",
            "access.token.claim": "true",
            "claim.name": "email_verified",
            "jsonType.label": "boolean"
          }
        }
      ]
    },
    {
      "name": "acr",
      "description": "OpenID Connect scope for add acr (authentication context class reference) to the token",
      "protocol": "openid-connect",
      "attributes": {
        "include.in.token.scope": "false",
        "display.on.consent.screen": "false"
      },
      "protocolMappers": [
        {
          "name": "acr loa level",
          "protocol": "openid-connect",
          "protocolMapper": "oidc-acr-mapper",
          "consentRequired": false,
          "config": {
            "id.token.claim": "true",
            "access.token.claim": "true",
            "userinfo.token.claim": "true"
          }
        }
      ]
    },
    {
      "name": "address",
      "description": "OpenID Connect built-in scope: address",
      "protocol": "openid-connect",
      "attributes": {
        "include.in.token.scope": "true",
        "display.on.consent.screen": "true",
        "consent.screen.text": "${addressScopeConsentText}"
      },
      "protocolMappers": [
        {
          "name": "address",
          "protocol": "openid-connect",
          "protocolMapper": "oidc-address-mapper",
          "consentRequired": false,
          "config": {
            "user.attribute.formatted": "formatted",
            "user.attribute.country": "country",
            "user.attribute.postal_code": "postal_code",
            "user.attribute.street": "street",
            "user.attribute.region": "region",
            "user.attribute.locality": "locality",
            "id.token.claim": "true",
            "access.token.claim": "true",
            "userinfo.token.claim": "true"
          }
        }
      ]
    },
    {
      "name": "phone",
      "description": "OpenID Connect built-in scope: phone",
      "protocol": "openid-connect",
      "attributes": {
        "include.in.token.scope": "true",
        "display.on.consent.screen": "true",
        "consent.screen.text": "${phoneScopeConsentText}"
      },
      "protocolMappers": [
        {
          "name": "phone number",
          "protocol": "openid-connect",
          "protocolMapper": "oidc-usermodel-attribute-mapper",
          "consentRequired": false,
          "config": {
            "userinfo.token.claim": "true",
            "user.attribute": "phoneNumber",
            "id.token.claim": "true",
            "access.token.claim": "true",
            "claim.name": "phone_number",
            "jsonType.label": "String"
          }
        },
        {
          "name": "phone number verified",
          "protocol": "openid-connect",
          "protocolMapper": "oidc-usermodel-attribute-mapper",
          "consentRequired": false,
          "config": {
            "userinfo.token.claim": "true",
            "user.attribute": "phoneNumberVerified",
            "id.token.claim": "true",
            "access.token.claim": "true",
            "claim.name": "phone_number_verified",
            "jsonType.label": "boolean"
          }
        }
      ]
    },
    {
      "name": "offline_access",
      "description": "OpenID Connect built-in scope: offline_access",
      "protocol": "openid-connect",
      "attributes": {
        "consent.screen.text": "${offlineAccessScopeConsentText}",
        "display.on.consent.screen": "true"
      }
    },
    {
      "name": "microprofile-jwt",
      "description": "Microprofile - JWT built-in scope",
      "protocol": "openid-connect",
      "attributes": {
        "include.in.token.scope": "true",
        "display.on.consent.screen": "false"
      },
      "protocolMappers": [
        {
          "name": "upn",
          "protocol": "openid-connect",
          "protocolMapper": "oidc-usermodel-attribute-mapper",
          "consentRequired": false,
          "config": {
            "userinfo.token.claim": "true",
            "user.attribute": "username",
            "id.token.claim": "true",
            "access.token.claim": "true",
            "claim.name": "upn",
            "jsonType.label": "String"
          }
        },
        {
          "name": "groups",
          "protocol": "openid-connect",
          "protocolMapper": "oidc-usermodel-realm-role-mapper",
          "consentRequired": false,
          "config": {
            "multivalued": "true",
            "id.token.claim": "true",
            "access.token.claim": "true",
            "claim.name": "groups",
            "jsonType.label": "String"
          }
        }
      ]
    }
  ],
  "defaultDefaultClientScopes": [
    "web-origins",
    "acr",
    "roles",
    "profile",
    "email"
  ],
  "defaultOptionalClientScopes": [
    "offline_access",
    "address",
    "phone",
    "microprofile-jwt"
  ],
  "browserFlow": "browser",
  "registrationFlow": "registration",
  "directGrantFlow": "direct grant",
  "resetCredentialsFlow": "reset credentials",
  "clientAuthenticationFlow": "clients"
}
